MANIFEST.in
README.md
requirements.txt
setup.py
test-requirements.txt
django_balanced/__init__.py
django_balanced/admin.py
django_balanced/context_processors.py
django_balanced/middleware.py
django_balanced/models.py
django_balanced/settings.py
django_balanced/tests.py
django_balanced/urls.py
django_balanced/views.py
django_balanced.egg-info/PKG-INFO
django_balanced.egg-info/SOURCES.txt
django_balanced.egg-info/dependency_links.txt
django_balanced.egg-info/requires.txt
django_balanced.egg-info/top_level.txt
django_balanced/management/__init__.py
django_balanced/management/commands/__init__.py
django_balanced/management/commands/sync.py
django_balanced/templates/django_balanced/admin_confirm_bulk_pay.html