Metadata-Version: 1.1
Name: django-balanced
Version: 0.1.10
Summary: Payments platform for marketplaces
Home-page: https://balancedpayments.com/
Author: Balanced
Author-email: support@balancedpayments.com
License: BSD
Platform: UNKNOWN
Classifier: Intended Audience :: Developers
Classifier: License :: OSI Approved :: BSD License
Classifier: Programming Language :: Python
Classifier: Topic :: Software Development :: Libraries :: Python Modules
